mqtt_cli.py
mqtt_cli-0.4.2.dist-info/licenses/LICENSE
mqtt_cli-0.4.2.dist-info/METADATA
mqtt_cli-0.4.2.dist-info/WHEEL
mqtt_cli-0.4.2.dist-info/entry_points.txt
mqtt_cli-0.4.2.dist-info/top_level.txt
mqtt_cli-0.4.2.dist-info/RECORD
