Metadata-Version: 2.4
Name: mqtt-cli
Version: 0.4.2
Summary: CLI for Paho MQTT
Home-page: https://github.com/MO-RISE/mqtt-cli
Author: Fredrik Olsson
Author-email: fredrik.x.olsson@ri.se
Maintainer: Fredrik Olsson
Maintainer-email: fredrik.x.olsson@ri.se
License: Apache License 2.0
Requires-Python: >=3.8
License-File: LICENSE
Requires-Dist: paho-mqtt>=2
Requires-Dist: parse
Requires-Dist: persist-queue
Dynamic: author
Dynamic: author-email
Dynamic: description
Dynamic: description-content-type
Dynamic: home-page
Dynamic: license
Dynamic: license-file
Dynamic: maintainer
Dynamic: maintainer-email
Dynamic: requires-dist
Dynamic: requires-python
Dynamic: summary
